README.md
setup.cfg
setup.py
adn_tools/__init__.py
adn_tools/execute_handler.py
adn_tools/item_handler.py
adn_tools/request_handler.py
adn_tools.egg-info/PKG-INFO
adn_tools.egg-info/SOURCES.txt
adn_tools.egg-info/dependency_links.txt
adn_tools.egg-info/not-zip-safe
adn_tools.egg-info/requires.txt
adn_tools.egg-info/top_level.txt