Metadata-Version: 1.0
Name: adn-tools
Version: 0.2
Summary: A helper that converts XLSX to api calls.
Home-page: https://gitlab.adnuntius.com/mickelun/adn-support-tools
Author: Mikael Lundin
Author-email: mikael@adnuntius.com
License: MIT
Platform: UNKNOWN
